RunDataTools/__init__.py
RunDataTools/for_arr.py
RunDataTools/for_df.py
RunDataTools/for_list.py
RunDataTools/for_str.py
RunDataTools/utils.py
RunDataTools-0.0.2.dist-info/DESCRIPTION.rst
RunDataTools-0.0.2.dist-info/METADATA
RunDataTools-0.0.2.dist-info/RECORD
RunDataTools-0.0.2.dist-info/WHEEL
RunDataTools-0.0.2.dist-info/metadata.json
RunDataTools-0.0.2.dist-info/top_level.txt
