Metadata-Version: 2.0
Name: RunDataTools
Version: 0.0.2
Summary: A Python library for transforming data format
Home-page: UNKNOWN
Author: Ijustwantyouhappy
Author-email: 18817363043@163.com
Maintainer: nobody
Maintainer-email: 
License: MIT
Platform: all
Classifier: Environment :: Web Environment
Classifier: Intended Audience :: Developers
Classifier: License :: OSI Approved :: MIT License
Classifier: Operating System :: MacOS
Classifier: Operating System :: Microsoft
Classifier: Operating System :: POSIX
Classifier: Operating System :: Unix
Classifier: Topic :: Internet
Classifier: Topic :: Software Development :: Libraries :: Python Modules
Classifier: Programming Language :: Python :: 3.5
Classifier: Programming Language :: Python :: 3.6
Classifier: Programming Language :: Python :: 3.7
Requires-Dist: numpy (>=1.16.3)
Requires-Dist: pandas (>=0.23.4)
